django_dragonpay_py3/__init__.py
django_dragonpay_py3/admin.py
django_dragonpay_py3/api/__init__.py
django_dragonpay_py3/api/http_get.py
django_dragonpay_py3/api/soap.py
django_dragonpay_py3/constants.py
django_dragonpay_py3/exceptions.py
django_dragonpay_py3/forms.py
django_dragonpay_py3/migrations/0001_initial.py
django_dragonpay_py3/migrations/0002_transaction_status_options.py
django_dragonpay_py3/migrations/0003_larger_max_length.py
django_dragonpay_py3/migrations/0004_auto_20210118_1234.py
django_dragonpay_py3/migrations/0005_auto_20210504_2237.py
django_dragonpay_py3/migrations/__init__.py
django_dragonpay_py3/models.py
django_dragonpay_py3/settings.py
django_dragonpay_py3/templates/dragonpay_soapxml/CancelTransaction.xml
django_dragonpay_py3/templates/dragonpay_soapxml/GetAvailableProcessors.xml
django_dragonpay_py3/templates/dragonpay_soapxml/GetPayoutData.xml
django_dragonpay_py3/templates/dragonpay_soapxml/GetPayoutTxnStatus.xml
django_dragonpay_py3/templates/dragonpay_soapxml/GetTxnToken.xml
django_dragonpay_py3/templates/dragonpay_soapxml/ModifyPayoutChannel.xml
django_dragonpay_py3/templates/dragonpay_soapxml/RegisterPayoutUser.xml
django_dragonpay_py3/templates/dragonpay_soapxml/RequestMultiplePayouts.xml
django_dragonpay_py3/templates/dragonpay_soapxml/RequestPayout.xml
django_dragonpay_py3/templates/dragonpay_soapxml/RequestPayoutEx.xml
django_dragonpay_py3/templates/dragonpay_soapxml/base.xml
django_dragonpay_py3/templates/dragonpay_soapxml/send_billing_info.xml
django_dragonpay_py3/templates/dragonpay_soapxml/webmethod.xml
django_dragonpay_py3/utils.py
django_dragonpay_py3/views.py
django_dragonpay_py3-0.1.5.dist-info/METADATA
django_dragonpay_py3-0.1.5.dist-info/WHEEL
django_dragonpay_py3-0.1.5.dist-info/RECORD
